polysecrets/__init__.py
polysecrets/cli.py
polysecrets/main.py
polysecrets/version.py
polysecrets-0.1.4.dist-info/METADATA
polysecrets-0.1.4.dist-info/WHEEL
polysecrets-0.1.4.dist-info/entry_points.txt
polysecrets-0.1.4.dist-info/top_level.txt
polysecrets-0.1.4.dist-info/RECORD
