Metadata-Version: 2.1
Name: polysecrets
Version: 0.1.4
Summary: A completely randomized order of secrets, with security in mind.
Home-page: https://github.com/ableinc/polysecrets
Author: AbleInc - Jaylen Douglas
Author-email: douglas.jaylen@gmail.com
License: UNKNOWN
Keywords: security,polysecrets,secrets,randomized,ableinc,cryptography,jwt,signing,encryption,server security,application security
Platform: UNKNOWN
Classifier: Programming Language :: Python :: 3.5
Classifier: Programming Language :: Python :: 3.6
Classifier: Programming Language :: Python :: 3.7
Classifier: Programming Language :: Python :: 3.8
Classifier: Programming Language :: Python :: 3 :: Only
Classifier: License :: OSI Approved :: MIT License
Classifier: Operating System :: OS Independent
Requires-Dist: Click (>=7.0)
Requires-Dist: pydotenvs
